alibabacloud_nbf_vpc_cloud20211115_131123360/__init__.py
alibabacloud_nbf_vpc_cloud20211115_131123360/client.py
alibabacloud_nbf_vpc_cloud20211115_131123360/models.py
alibabacloud_nbf_vpc_cloud20211115_131123360-1.0.0.dist-info/LICENSE
alibabacloud_nbf_vpc_cloud20211115_131123360-1.0.0.dist-info/METADATA
alibabacloud_nbf_vpc_cloud20211115_131123360-1.0.0.dist-info/WHEEL
alibabacloud_nbf_vpc_cloud20211115_131123360-1.0.0.dist-info/top_level.txt
alibabacloud_nbf_vpc_cloud20211115_131123360-1.0.0.dist-info/RECORD
